imodif/__init__.py
imodif/bright.py
imodif/dark.py
imodif/dim.py
imodif-1.0.21.dist-info/LICENSE
imodif-1.0.21.dist-info/METADATA
imodif-1.0.21.dist-info/WHEEL
imodif-1.0.21.dist-info/top_level.txt
imodif-1.0.21.dist-info/RECORD
