Metadata-Version: 2.1
Name: imodif
Version: 1.0.21
Summary: An image modification package.
Home-page: UNKNOWN
Author: Abiah Sylvester
Author-email: abiahsylvester759@gmail.com
License: MIT
Keywords: python,image,modifier,darkness,brightness,contrast
Platform: UNKNOWN
Classifier: Development Status :: 3 - Alpha
Classifier: Intended Audience :: Developers
Classifier: License :: OSI Approved :: MIT License
Classifier: Programming Language :: Python :: 3
Classifier: Operating System :: MacOS :: MacOS X
Classifier: Operating System :: Microsoft :: Windows
Requires-Python: >=3.8
License-File: LICENSE
Requires-Dist: numpy
Requires-Dist: opencv-python
